https/__init__.py
https/server.py
https.server-1.2.0.dist-info/LICENSE
https.server-1.2.0.dist-info/METADATA
https.server-1.2.0.dist-info/WHEEL
https.server-1.2.0.dist-info/entry_points.txt
https.server-1.2.0.dist-info/top_level.txt
https.server-1.2.0.dist-info/RECORD
